LICENSE
MANIFEST.in
README.rst
setup.py
il2fb/commons/__init__.py
il2fb/commons/actors.py
il2fb/commons/events.py
il2fb/commons/exceptions.py
il2fb/commons/flight.py
il2fb/commons/organization.py
il2fb/commons/regex.py
il2fb/commons/spatial.py
il2fb/commons/structures.py
il2fb/commons/targets.py
il2fb/commons/transformers.py
il2fb/commons/utils.py
il2fb/commons/weather.py
il2fb/commons/locale/en/LC_MESSAGES/il2fb-commons.mo
il2fb/commons/locale/en/LC_MESSAGES/il2fb-commons.po
il2fb/commons/locale/ru/LC_MESSAGES/il2fb-commons.mo
il2fb/commons/locale/ru/LC_MESSAGES/il2fb-commons.po
il2fb_commons.egg-info/PKG-INFO
il2fb_commons.egg-info/SOURCES.txt
il2fb_commons.egg-info/dependency_links.txt
il2fb_commons.egg-info/namespace_packages.txt
il2fb_commons.egg-info/pbr.json
il2fb_commons.egg-info/requires.txt
il2fb_commons.egg-info/top_level.txt
requirements/dist.txt